Metadata-Version: 1.1
Name: WhichFile
Version: 1.0.3
Summary: Reports symlink targets and file types, like `which` and `file`.
